[
  {
    "model": "ICON-D2",
    "run_date": "20260328",
    "run_hour": "15",
    "step_h": 0,
    "valid_time": "2026-03-28T15:00Z",
    "target_lat": 48.71,
    "target_lon": 8.784,
    "grid_lat": 48.71,
    "grid_lon": 8.784,
    "surface_p_hPa": 957.15,
    "n_levels_loaded": 65,
    "levels": [
      {
        "level_idx": 65,
        "p_hPa": 955.966,
        "z_m": 9.9,
        "T_C": 0.93,
        "Td_C": 0.5,
        "wspd_kn": 1.5,
        "wdir_deg": 260.7
      },
      {
        "level_idx": 64,
        "p_hPa": 952.861,
        "z_m": 36.0,
        "T_C": 0.64,
        "Td_C": 0.39,
        "wspd_kn": 1.7,
        "wdir_deg": 259.5
      },
      {
        "level_idx": 63,
        "p_hPa": 948.471,
        "z_m": 73.0,
        "T_C": 0.3,
        "Td_C": 0.21,
        "wspd_kn": 2.0,
        "wdir_deg": 256.6
      },
      {
        "level_idx": 62,
        "p_hPa": 943.104,
        "z_m": 118.3,
        "T_C": 0.12,
        "Td_C": 0.05,
        "wspd_kn": 2.5,
        "wdir_deg": 253.8
      },
      {
        "level_idx": 61,
        "p_hPa": 936.976,
        "z_m": 170.4,
        "T_C": -0.15,
        "Td_C": -0.18,
        "wspd_kn": 3.1,
        "wdir_deg": 269.8
      },
      {
        "level_idx": 60,
        "p_hPa": 930.182,
        "z_m": 228.5,
        "T_C": -0.42,
        "Td_C": -0.44,
        "wspd_kn": 3.7,
        "wdir_deg": 281.2
      },
      {
        "level_idx": 59,
        "p_hPa": 922.794,
        "z_m": 292.1,
        "T_C": -0.81,
        "Td_C": -0.91,
        "wspd_kn": 4.6,
        "wdir_deg": 283.6
      },
      {
        "level_idx": 58,
        "p_hPa": 914.843,
        "z_m": 361.0,
        "T_C": -1.26,
        "Td_C": -1.61,
        "wspd_kn": 6.0,
        "wdir_deg": 277.6
      },
      {
        "level_idx": 57,
        "p_hPa": 906.378,
        "z_m": 434.8,
        "T_C": -1.85,
        "Td_C": -2.29,
        "wspd_kn": 8.2,
        "wdir_deg": 272.5
      },
      {
        "level_idx": 56,
        "p_hPa": 897.415,
        "z_m": 513.5,
        "T_C": -2.56,
        "Td_C": -2.73,
        "wspd_kn": 10.3,
        "wdir_deg": 272.0
      },
      {
        "level_idx": 55,
        "p_hPa": 887.978,
        "z_m": 597.1,
        "T_C": -3.17,
        "Td_C": -3.51,
        "wspd_kn": 13.1,
        "wdir_deg": 273.2
      },
      {
        "level_idx": 54,
        "p_hPa": 878.101,
        "z_m": 685.3,
        "T_C": -3.75,
        "Td_C": -4.19,
        "wspd_kn": 16.2,
        "wdir_deg": 275.5
      },
      {
        "level_idx": 53,
        "p_hPa": 867.797,
        "z_m": 778.1,
        "T_C": -4.38,
        "Td_C": -4.86,
        "wspd_kn": 17.4,
        "wdir_deg": 277.8
      },
      {
        "level_idx": 52,
        "p_hPa": 857.073,
        "z_m": 875.8,
        "T_C": -4.87,
        "Td_C": -5.46,
        "wspd_kn": 17.8,
        "wdir_deg": 281.2
      },
      {
        "level_idx": 51,
        "p_hPa": 845.965,
        "z_m": 978.1,
        "T_C": -5.24,
        "Td_C": -5.85,
        "wspd_kn": 17.0,
        "wdir_deg": 284.2
      },
      {
        "level_idx": 50,
        "p_hPa": 834.481,
        "z_m": 1085.2,
        "T_C": -5.49,
        "Td_C": -6.07,
        "wspd_kn": 16.5,
        "wdir_deg": 285.5
      },
      {
        "level_idx": 49,
        "p_hPa": 822.646,
        "z_m": 1197.1,
        "T_C": -5.5,
        "Td_C": -6.13,
        "wspd_kn": 16.1,
        "wdir_deg": 284.4
      },
      {
        "level_idx": 48,
        "p_hPa": 810.474,
        "z_m": 1313.8,
        "T_C": -5.55,
        "Td_C": -6.09,
        "wspd_kn": 16.3,
        "wdir_deg": 284.7
      },
      {
        "level_idx": 47,
        "p_hPa": 797.979,
        "z_m": 1435.5,
        "T_C": -5.58,
        "Td_C": -6.01,
        "wspd_kn": 16.4,
        "wdir_deg": 283.5
      },
      {
        "level_idx": 46,
        "p_hPa": 785.169,
        "z_m": 1562.2,
        "T_C": -5.71,
        "Td_C": -6.08,
        "wspd_kn": 16.2,
        "wdir_deg": 282.3
      },
      {
        "level_idx": 45,
        "p_hPa": 772.046,
        "z_m": 1694.0,
        "T_C": -6.04,
        "Td_C": -6.39,
        "wspd_kn": 16.0,
        "wdir_deg": 281.9
      },
      {
        "level_idx": 44,
        "p_hPa": 758.615,
        "z_m": 1831.0,
        "T_C": -6.54,
        "Td_C": -6.97,
        "wspd_kn": 16.1,
        "wdir_deg": 281.0
      },
      {
        "level_idx": 43,
        "p_hPa": 744.873,
        "z_m": 1973.3,
        "T_C": -7.12,
        "Td_C": -7.67,
        "wspd_kn": 16.2,
        "wdir_deg": 279.5
      },
      {
        "level_idx": 42,
        "p_hPa": 730.837,
        "z_m": 2121.2,
        "T_C": -7.7,
        "Td_C": -8.32,
        "wspd_kn": 16.2,
        "wdir_deg": 278.2
      },
      {
        "level_idx": 41,
        "p_hPa": 716.504,
        "z_m": 2274.7,
        "T_C": -8.25,
        "Td_C": -8.88,
        "wspd_kn": 15.9,
        "wdir_deg": 275.8
      },
      {
        "level_idx": 40,
        "p_hPa": 701.893,
        "z_m": 2434.1,
        "T_C": -8.93,
        "Td_C": -9.54,
        "wspd_kn": 15.4,
        "wdir_deg": 274.7
      },
      {
        "level_idx": 39,
        "p_hPa": 687.008,
        "z_m": 2599.4,
        "T_C": -9.65,
        "Td_C": -10.23,
        "wspd_kn": 14.8,
        "wdir_deg": 270.9
      },
      {
        "level_idx": 38,
        "p_hPa": 671.848,
        "z_m": 2770.9,
        "T_C": -10.51,
        "Td_C": -11.13,
        "wspd_kn": 14.7,
        "wdir_deg": 269.0
      },
      {
        "level_idx": 37,
        "p_hPa": 656.424,
        "z_m": 2948.8,
        "T_C": -11.49,
        "Td_C": -12.2,
        "wspd_kn": 14.8,
        "wdir_deg": 267.1
      },
      {
        "level_idx": 36,
        "p_hPa": 640.739,
        "z_m": 3133.3,
        "T_C": -12.59,
        "Td_C": -13.38,
        "wspd_kn": 14.7,
        "wdir_deg": 266.3
      },
      {
        "level_idx": 35,
        "p_hPa": 624.797,
        "z_m": 3324.6,
        "T_C": -13.79,
        "Td_C": -14.75,
        "wspd_kn": 16.2,
        "wdir_deg": 264.7
      },
      {
        "level_idx": 34,
        "p_hPa": 608.61,
        "z_m": 3523.0,
        "T_C": -14.9,
        "Td_C": -16.07,
        "wspd_kn": 17.2,
        "wdir_deg": 267.2
      },
      {
        "level_idx": 33,
        "p_hPa": 592.19,
        "z_m": 3728.7,
        "T_C": -16.26,
        "Td_C": -17.63,
        "wspd_kn": 17.1,
        "wdir_deg": 270.7
      },
      {
        "level_idx": 32,
        "p_hPa": 575.545,
        "z_m": 3942.0,
        "T_C": -17.52,
        "Td_C": -19.03,
        "wspd_kn": 16.4,
        "wdir_deg": 266.3
      },
      {
        "level_idx": 31,
        "p_hPa": 558.683,
        "z_m": 4163.2,
        "T_C": -18.99,
        "Td_C": -20.58,
        "wspd_kn": 15.8,
        "wdir_deg": 267.6
      },
      {
        "level_idx": 30,
        "p_hPa": 541.622,
        "z_m": 4392.7,
        "T_C": -20.36,
        "Td_C": -22.15,
        "wspd_kn": 15.3,
        "wdir_deg": 261.8
      },
      {
        "level_idx": 29,
        "p_hPa": 524.376,
        "z_m": 4630.7,
        "T_C": -21.91,
        "Td_C": -23.86,
        "wspd_kn": 14.9,
        "wdir_deg": 256.6
      },
      {
        "level_idx": 28,
        "p_hPa": 506.95,
        "z_m": 4877.6,
        "T_C": -23.61,
        "Td_C": -25.73,
        "wspd_kn": 15.0,
        "wdir_deg": 254.5
      },
      {
        "level_idx": 27,
        "p_hPa": 489.356,
        "z_m": 5133.7,
        "T_C": -25.4,
        "Td_C": -27.43,
        "wspd_kn": 14.8,
        "wdir_deg": 245.3
      },
      {
        "level_idx": 26,
        "p_hPa": 471.604,
        "z_m": 5399.6,
        "T_C": -27.36,
        "Td_C": -29.47,
        "wspd_kn": 18.3,
        "wdir_deg": 251.5
      },
      {
        "level_idx": 25,
        "p_hPa": 453.701,
        "z_m": 5675.5,
        "T_C": -29.56,
        "Td_C": -32.0,
        "wspd_kn": 17.0,
        "wdir_deg": 250.8
      },
      {
        "level_idx": 24,
        "p_hPa": 435.665,
        "z_m": 5962.3,
        "T_C": -31.66,
        "Td_C": -35.74,
        "wspd_kn": 19.5,
        "wdir_deg": 246.2
      },
      {
        "level_idx": 23,
        "p_hPa": 417.549,
        "z_m": 6260.7,
        "T_C": -33.13,
        "Td_C": -37.33,
        "wspd_kn": 22.0,
        "wdir_deg": 238.9
      },
      {
        "level_idx": 22,
        "p_hPa": 399.375,
        "z_m": 6570.6,
        "T_C": -35.19,
        "Td_C": -38.42,
        "wspd_kn": 25.4,
        "wdir_deg": 232.1
      },
      {
        "level_idx": 21,
        "p_hPa": 381.131,
        "z_m": 6892.9,
        "T_C": -37.73,
        "Td_C": -41.26,
        "wspd_kn": 29.2,
        "wdir_deg": 233.6
      },
      {
        "level_idx": 20,
        "p_hPa": 362.814,
        "z_m": 7228.1,
        "T_C": -40.59,
        "Td_C": -44.36,
        "wspd_kn": 30.2,
        "wdir_deg": 236.2
      },
      {
        "level_idx": 19,
        "p_hPa": 344.446,
        "z_m": 7577.7,
        "T_C": -43.32,
        "Td_C": -47.79,
        "wspd_kn": 32.2,
        "wdir_deg": 239.6
      },
      {
        "level_idx": 18,
        "p_hPa": 326.055,
        "z_m": 7942.1,
        "T_C": -46.26,
        "Td_C": -51.14,
        "wspd_kn": 33.4,
        "wdir_deg": 240.3
      },
      {
        "level_idx": 17,
        "p_hPa": 307.653,
        "z_m": 8322.4,
        "T_C": -49.51,
        "Td_C": -53.97,
        "wspd_kn": 34.9,
        "wdir_deg": 246.9
      },
      {
        "level_idx": 16,
        "p_hPa": 289.27,
        "z_m": 8720.2,
        "T_C": -52.58,
        "Td_C": -58.83,
        "wspd_kn": 41.4,
        "wdir_deg": 254.7
      },
      {
        "level_idx": 15,
        "p_hPa": 270.971,
        "z_m": 9137.1,
        "T_C": -55.18,
        "Td_C": -63.47,
        "wspd_kn": 40.3,
        "wdir_deg": 259.4
      },
      {
        "level_idx": 14,
        "p_hPa": 252.914,
        "z_m": 9577.0,
        "T_C": -55.26,
        "Td_C": -70.4,
        "wspd_kn": 32.7,
        "wdir_deg": 257.6
      },
      {
        "level_idx": 13,
        "p_hPa": 235.3,
        "z_m": 10041.3,
        "T_C": -53.43,
        "Td_C": -74.43,
        "wspd_kn": 27.0,
        "wdir_deg": 249.8
      },
      {
        "level_idx": 12,
        "p_hPa": 218.247,
        "z_m": 10531.6,
        "T_C": -50.52,
        "Td_C": -79.94,
        "wspd_kn": 30.9,
        "wdir_deg": 254.0
      },
      {
        "level_idx": 11,
        "p_hPa": 201.818,
        "z_m": 11050.8,
        "T_C": -46.5,
        "Td_C": -81.21,
        "wspd_kn": 23.1,
        "wdir_deg": 272.0
      },
      {
        "level_idx": 10,
        "p_hPa": 185.858,
        "z_m": 11595.5,
        "T_C": -47.29,
        "Td_C": -81.43,
        "wspd_kn": 21.7,
        "wdir_deg": 277.2
      },
      {
        "level_idx": 9,
        "p_hPa": 170.197,
        "z_m": 12175.2,
        "T_C": -48.15,
        "Td_C": -82.97,
        "wspd_kn": 21.6,
        "wdir_deg": 295.6
      },
      {
        "level_idx": 8,
        "p_hPa": 154.825,
        "z_m": 12794.7,
        "T_C": -49.58,
        "Td_C": -83.5,
        "wspd_kn": 16.1,
        "wdir_deg": 303.3
      },
      {
        "level_idx": 7,
        "p_hPa": 139.728,
        "z_m": 13461.9,
        "T_C": -50.99,
        "Td_C": -85.88,
        "wspd_kn": 20.1,
        "wdir_deg": 307.3
      },
      {
        "level_idx": 6,
        "p_hPa": 124.907,
        "z_m": 14186.6,
        "T_C": -52.33,
        "Td_C": -86.44,
        "wspd_kn": 19.9,
        "wdir_deg": 322.2
      },
      {
        "level_idx": 5,
        "p_hPa": 110.294,
        "z_m": 14980.8,
        "T_C": -55.11,
        "Td_C": -88.79,
        "wspd_kn": 19.9,
        "wdir_deg": 336.0
      },
      {
        "level_idx": 4,
        "p_hPa": 95.84,
        "z_m": 15869.3,
        "T_C": -57.04,
        "Td_C": -87.85,
        "wspd_kn": 16.3,
        "wdir_deg": 345.1
      },
      {
        "level_idx": 3,
        "p_hPa": 81.446,
        "z_m": 16893.0,
        "T_C": -58.27,
        "Td_C": -87.82,
        "wspd_kn": 11.4,
        "wdir_deg": 345.6
      },
      {
        "level_idx": 2,
        "p_hPa": 66.788,
        "z_m": 18140.7,
        "T_C": -58.33,
        "Td_C": -88.42,
        "wspd_kn": 8.1,
        "wdir_deg": 347.2
      },
      {
        "level_idx": 1,
        "p_hPa": 48.612,
        "z_m": 20132.0,
        "T_C": -58.98,
        "Td_C": -89.99,
        "wspd_kn": 3.3,
        "wdir_deg": 328.6
      }
    ]
  },
  {
    "model": "ICON-D2",
    "run_date": "20260328",
    "run_hour": "15",
    "step_h": 6,
    "valid_time": "2026-03-28T21:00Z",
    "target_lat": 48.71,
    "target_lon": 8.784,
    "grid_lat": 48.71,
    "grid_lon": 8.784,
    "surface_p_hPa": 959.97,
    "n_levels_loaded": 65,
    "levels": [
      {
        "level_idx": 65,
        "p_hPa": 958.783,
        "z_m": 10.0,
        "T_C": 1.4,
        "Td_C": 0.39,
        "wspd_kn": 3.9,
        "wdir_deg": 323.6
      },
      {
        "level_idx": 64,
        "p_hPa": 955.683,
        "z_m": 36.0,
        "T_C": 1.25,
        "Td_C": 0.28,
        "wspd_kn": 6.2,
        "wdir_deg": 325.9
      },
      {
        "level_idx": 63,
        "p_hPa": 951.295,
        "z_m": 72.9,
        "T_C": 1.02,
        "Td_C": 0.16,
        "wspd_kn": 8.7,
        "wdir_deg": 327.0
      },
      {
        "level_idx": 62,
        "p_hPa": 945.923,
        "z_m": 118.3,
        "T_C": 0.7,
        "Td_C": 0.05,
        "wspd_kn": 11.1,
        "wdir_deg": 328.2
      },
      {
        "level_idx": 61,
        "p_hPa": 939.792,
        "z_m": 170.4,
        "T_C": 0.33,
        "Td_C": -0.04,
        "wspd_kn": 14.3,
        "wdir_deg": 329.7
      },
      {
        "level_idx": 60,
        "p_hPa": 932.985,
        "z_m": 228.5,
        "T_C": -0.05,
        "Td_C": -0.13,
        "wspd_kn": 17.2,
        "wdir_deg": 332.0
      },
      {
        "level_idx": 59,
        "p_hPa": 925.584,
        "z_m": 292.1,
        "T_C": -0.36,
        "Td_C": -0.36,
        "wspd_kn": 19.3,
        "wdir_deg": 335.5
      },
      {
        "level_idx": 58,
        "p_hPa": 917.63,
        "z_m": 360.9,
        "T_C": -0.72,
        "Td_C": -0.72,
        "wspd_kn": 21.2,
        "wdir_deg": 342.2
      },
      {
        "level_idx": 57,
        "p_hPa": 909.152,
        "z_m": 434.8,
        "T_C": -1.14,
        "Td_C": -1.15,
        "wspd_kn": 22.7,
        "wdir_deg": 349.2
      },
      {
        "level_idx": 56,
        "p_hPa": 900.195,
        "z_m": 513.5,
        "T_C": -1.67,
        "Td_C": -1.68,
        "wspd_kn": 23.9,
        "wdir_deg": 353.6
      },
      {
        "level_idx": 55,
        "p_hPa": 890.764,
        "z_m": 597.0,
        "T_C": -2.27,
        "Td_C": -2.27,
        "wspd_kn": 24.7,
        "wdir_deg": 356.5
      },
      {
        "level_idx": 54,
        "p_hPa": 880.891,
        "z_m": 685.2,
        "T_C": -2.81,
        "Td_C": -2.81,
        "wspd_kn": 25.0,
        "wdir_deg": 357.8
      },
      {
        "level_idx": 53,
        "p_hPa": 870.592,
        "z_m": 778.1,
        "T_C": -3.26,
        "Td_C": -3.27,
        "wspd_kn": 25.5,
        "wdir_deg": 359.1
      },
      {
        "level_idx": 52,
        "p_hPa": 859.893,
        "z_m": 875.6,
        "T_C": -3.89,
        "Td_C": -3.89,
        "wspd_kn": 25.6,
        "wdir_deg": 359.3
      },
      {
        "level_idx": 51,
        "p_hPa": 848.782,
        "z_m": 977.8,
        "T_C": -4.52,
        "Td_C": -4.52,
        "wspd_kn": 25.1,
        "wdir_deg": 358.6
      },
      {
        "level_idx": 50,
        "p_hPa": 837.281,
        "z_m": 1084.9,
        "T_C": -5.18,
        "Td_C": -5.19,
        "wspd_kn": 24.4,
        "wdir_deg": 357.6
      },
      {
        "level_idx": 49,
        "p_hPa": 825.407,
        "z_m": 1196.6,
        "T_C": -5.96,
        "Td_C": -5.97,
        "wspd_kn": 23.9,
        "wdir_deg": 357.3
      },
      {
        "level_idx": 48,
        "p_hPa": 813.161,
        "z_m": 1313.1,
        "T_C": -6.73,
        "Td_C": -6.74,
        "wspd_kn": 23.2,
        "wdir_deg": 357.3
      },
      {
        "level_idx": 47,
        "p_hPa": 800.55,
        "z_m": 1434.7,
        "T_C": -7.47,
        "Td_C": -7.81,
        "wspd_kn": 22.7,
        "wdir_deg": 357.5
      },
      {
        "level_idx": 46,
        "p_hPa": 787.593,
        "z_m": 1561.2,
        "T_C": -8.28,
        "Td_C": -8.81,
        "wspd_kn": 22.2,
        "wdir_deg": 357.5
      },
      {
        "level_idx": 45,
        "p_hPa": 774.288,
        "z_m": 1692.9,
        "T_C": -9.17,
        "Td_C": -9.84,
        "wspd_kn": 21.5,
        "wdir_deg": 356.6
      },
      {
        "level_idx": 44,
        "p_hPa": 760.643,
        "z_m": 1829.8,
        "T_C": -10.04,
        "Td_C": -10.71,
        "wspd_kn": 20.9,
        "wdir_deg": 355.3
      },
      {
        "level_idx": 43,
        "p_hPa": 746.676,
        "z_m": 1972.1,
        "T_C": -10.84,
        "Td_C": -11.7,
        "wspd_kn": 20.0,
        "wdir_deg": 353.5
      },
      {
        "level_idx": 42,
        "p_hPa": 732.383,
        "z_m": 2119.9,
        "T_C": -11.91,
        "Td_C": -13.18,
        "wspd_kn": 19.6,
        "wdir_deg": 351.2
      },
      {
        "level_idx": 41,
        "p_hPa": 717.768,
        "z_m": 2273.3,
        "T_C": -13.17,
        "Td_C": -14.84,
        "wspd_kn": 19.1,
        "wdir_deg": 347.1
      },
      {
        "level_idx": 40,
        "p_hPa": 702.832,
        "z_m": 2432.5,
        "T_C": -14.45,
        "Td_C": -16.34,
        "wspd_kn": 17.2,
        "wdir_deg": 343.1
      },
      {
        "level_idx": 39,
        "p_hPa": 687.598,
        "z_m": 2597.8,
        "T_C": -15.43,
        "Td_C": -17.28,
        "wspd_kn": 13.2,
        "wdir_deg": 334.9
      },
      {
        "level_idx": 38,
        "p_hPa": 672.1,
        "z_m": 2769.7,
        "T_C": -15.68,
        "Td_C": -19.95,
        "wspd_kn": 10.0,
        "wdir_deg": 292.7
      },
      {
        "level_idx": 37,
        "p_hPa": 656.383,
        "z_m": 2948.0,
        "T_C": -15.66,
        "Td_C": -24.58,
        "wspd_kn": 10.3,
        "wdir_deg": 292.0
      },
      {
        "level_idx": 36,
        "p_hPa": 640.455,
        "z_m": 3132.8,
        "T_C": -16.15,
        "Td_C": -27.71,
        "wspd_kn": 9.6,
        "wdir_deg": 282.2
      },
      {
        "level_idx": 35,
        "p_hPa": 624.302,
        "z_m": 3324.3,
        "T_C": -17.04,
        "Td_C": -29.4,
        "wspd_kn": 9.7,
        "wdir_deg": 269.6
      },
      {
        "level_idx": 34,
        "p_hPa": 607.929,
        "z_m": 3523.0,
        "T_C": -17.73,
        "Td_C": -33.04,
        "wspd_kn": 9.6,
        "wdir_deg": 256.9
      },
      {
        "level_idx": 33,
        "p_hPa": 591.345,
        "z_m": 3729.0,
        "T_C": -18.79,
        "Td_C": -37.41,
        "wspd_kn": 9.7,
        "wdir_deg": 251.3
      },
      {
        "level_idx": 32,
        "p_hPa": 574.553,
        "z_m": 3942.5,
        "T_C": -19.85,
        "Td_C": -40.81,
        "wspd_kn": 10.9,
        "wdir_deg": 254.0
      },
      {
        "level_idx": 31,
        "p_hPa": 557.572,
        "z_m": 4164.0,
        "T_C": -21.0,
        "Td_C": -41.17,
        "wspd_kn": 14.2,
        "wdir_deg": 256.7
      },
      {
        "level_idx": 30,
        "p_hPa": 540.394,
        "z_m": 4393.5,
        "T_C": -22.53,
        "Td_C": -39.98,
        "wspd_kn": 16.5,
        "wdir_deg": 253.1
      },
      {
        "level_idx": 29,
        "p_hPa": 523.033,
        "z_m": 4631.6,
        "T_C": -24.08,
        "Td_C": -41.48,
        "wspd_kn": 18.5,
        "wdir_deg": 242.8
      },
      {
        "level_idx": 28,
        "p_hPa": 505.486,
        "z_m": 4878.5,
        "T_C": -26.0,
        "Td_C": -45.42,
        "wspd_kn": 18.9,
        "wdir_deg": 232.8
      },
      {
        "level_idx": 27,
        "p_hPa": 487.777,
        "z_m": 5134.9,
        "T_C": -27.54,
        "Td_C": -53.85,
        "wspd_kn": 21.7,
        "wdir_deg": 225.9
      },
      {
        "level_idx": 26,
        "p_hPa": 469.914,
        "z_m": 5400.7,
        "T_C": -29.79,
        "Td_C": -55.75,
        "wspd_kn": 23.8,
        "wdir_deg": 220.3
      },
      {
        "level_idx": 25,
        "p_hPa": 451.905,
        "z_m": 5676.8,
        "T_C": -31.69,
        "Td_C": -41.31,
        "wspd_kn": 25.6,
        "wdir_deg": 206.4
      },
      {
        "level_idx": 24,
        "p_hPa": 433.765,
        "z_m": 5963.4,
        "T_C": -34.25,
        "Td_C": -44.85,
        "wspd_kn": 26.3,
        "wdir_deg": 212.8
      },
      {
        "level_idx": 23,
        "p_hPa": 415.524,
        "z_m": 6261.7,
        "T_C": -35.93,
        "Td_C": -51.63,
        "wspd_kn": 29.8,
        "wdir_deg": 212.4
      },
      {
        "level_idx": 22,
        "p_hPa": 397.218,
        "z_m": 6571.5,
        "T_C": -38.2,
        "Td_C": -51.74,
        "wspd_kn": 32.3,
        "wdir_deg": 213.4
      },
      {
        "level_idx": 21,
        "p_hPa": 378.85,
        "z_m": 6893.9,
        "T_C": -40.56,
        "Td_C": -50.27,
        "wspd_kn": 35.1,
        "wdir_deg": 215.0
      },
      {
        "level_idx": 20,
        "p_hPa": 360.45,
        "z_m": 7229.6,
        "T_C": -42.74,
        "Td_C": -49.1,
        "wspd_kn": 39.5,
        "wdir_deg": 217.0
      },
      {
        "level_idx": 19,
        "p_hPa": 342.042,
        "z_m": 7579.3,
        "T_C": -45.28,
        "Td_C": -49.18,
        "wspd_kn": 43.1,
        "wdir_deg": 214.8
      },
      {
        "level_idx": 18,
        "p_hPa": 323.618,
        "z_m": 7943.6,
        "T_C": -48.4,
        "Td_C": -52.23,
        "wspd_kn": 44.9,
        "wdir_deg": 214.7
      },
      {
        "level_idx": 17,
        "p_hPa": 305.183,
        "z_m": 8323.8,
        "T_C": -51.66,
        "Td_C": -57.53,
        "wspd_kn": 48.1,
        "wdir_deg": 219.3
      },
      {
        "level_idx": 16,
        "p_hPa": 286.834,
        "z_m": 8722.8,
        "T_C": -53.33,
        "Td_C": -66.92,
        "wspd_kn": 45.3,
        "wdir_deg": 226.5
      },
      {
        "level_idx": 15,
        "p_hPa": 268.754,
        "z_m": 9142.7,
        "T_C": -52.87,
        "Td_C": -73.2,
        "wspd_kn": 36.6,
        "wdir_deg": 232.8
      },
      {
        "level_idx": 14,
        "p_hPa": 251.092,
        "z_m": 9584.1,
        "T_C": -51.27,
        "Td_C": -77.89,
        "wspd_kn": 26.9,
        "wdir_deg": 240.5
      },
      {
        "level_idx": 13,
        "p_hPa": 233.887,
        "z_m": 10047.8,
        "T_C": -49.97,
        "Td_C": -80.58,
        "wspd_kn": 20.3,
        "wdir_deg": 255.2
      },
      {
        "level_idx": 12,
        "p_hPa": 217.163,
        "z_m": 10537.4,
        "T_C": -47.74,
        "Td_C": -81.31,
        "wspd_kn": 19.7,
        "wdir_deg": 272.1
      },
      {
        "level_idx": 11,
        "p_hPa": 200.968,
        "z_m": 11055.2,
        "T_C": -44.87,
        "Td_C": -81.74,
        "wspd_kn": 15.0,
        "wdir_deg": 282.5
      },
      {
        "level_idx": 10,
        "p_hPa": 185.219,
        "z_m": 11601.2,
        "T_C": -44.62,
        "Td_C": -82.37,
        "wspd_kn": 10.7,
        "wdir_deg": 280.7
      },
      {
        "level_idx": 9,
        "p_hPa": 169.755,
        "z_m": 12179.7,
        "T_C": -46.45,
        "Td_C": -82.97,
        "wspd_kn": 13.3,
        "wdir_deg": 261.9
      },
      {
        "level_idx": 8,
        "p_hPa": 154.538,
        "z_m": 12799.4,
        "T_C": -47.72,
        "Td_C": -83.2,
        "wspd_kn": 19.9,
        "wdir_deg": 283.6
      },
      {
        "level_idx": 7,
        "p_hPa": 139.593,
        "z_m": 13466.8,
        "T_C": -48.98,
        "Td_C": -83.15,
        "wspd_kn": 20.6,
        "wdir_deg": 300.6
      },
      {
        "level_idx": 6,
        "p_hPa": 124.895,
        "z_m": 14190.9,
        "T_C": -50.83,
        "Td_C": -84.88,
        "wspd_kn": 17.1,
        "wdir_deg": 316.4
      },
      {
        "level_idx": 5,
        "p_hPa": 110.364,
        "z_m": 14984.3,
        "T_C": -54.0,
        "Td_C": -85.81,
        "wspd_kn": 13.9,
        "wdir_deg": 321.0
      },
      {
        "level_idx": 4,
        "p_hPa": 95.948,
        "z_m": 15871.6,
        "T_C": -56.61,
        "Td_C": -88.97,
        "wspd_kn": 13.1,
        "wdir_deg": 329.8
      },
      {
        "level_idx": 3,
        "p_hPa": 81.575,
        "z_m": 16896.0,
        "T_C": -57.51,
        "Td_C": -88.21,
        "wspd_kn": 11.6,
        "wdir_deg": 333.5
      },
      {
        "level_idx": 2,
        "p_hPa": 66.915,
        "z_m": 18141.8,
        "T_C": -58.3,
        "Td_C": -88.45,
        "wspd_kn": 8.7,
        "wdir_deg": 353.4
      },
      {
        "level_idx": 1,
        "p_hPa": 48.704,
        "z_m": 20132.9,
        "T_C": -59.02,
        "Td_C": -89.98,
        "wspd_kn": 5.2,
        "wdir_deg": 55.3
      }
    ]
  },
  {
    "model": "ICON-D2",
    "run_date": "20260328",
    "run_hour": "15",
    "step_h": 12,
    "valid_time": "2026-03-29T03:00Z",
    "target_lat": 48.71,
    "target_lon": 8.784,
    "grid_lat": 48.71,
    "grid_lon": 8.784,
    "surface_p_hPa": 962.01,
    "n_levels_loaded": 65,
    "levels": [
      {
        "level_idx": 65,
        "p_hPa": 960.816,
        "z_m": 10.0,
        "T_C": 0.73,
        "Td_C": -0.36,
        "wspd_kn": 3.5,
        "wdir_deg": 323.4
      },
      {
        "level_idx": 64,
        "p_hPa": 957.7,
        "z_m": 36.0,
        "T_C": 0.68,
        "Td_C": -0.41,
        "wspd_kn": 5.9,
        "wdir_deg": 326.4
      },
      {
        "level_idx": 63,
        "p_hPa": 953.292,
        "z_m": 73.0,
        "T_C": 0.49,
        "Td_C": -0.5,
        "wspd_kn": 8.5,
        "wdir_deg": 327.6
      },
      {
        "level_idx": 62,
        "p_hPa": 947.9,
        "z_m": 118.4,
        "T_C": 0.25,
        "Td_C": -0.64,
        "wspd_kn": 11.5,
        "wdir_deg": 329.5
      },
      {
        "level_idx": 61,
        "p_hPa": 941.748,
        "z_m": 170.4,
        "T_C": -0.06,
        "Td_C": -0.86,
        "wspd_kn": 14.6,
        "wdir_deg": 332.8
      },
      {
        "level_idx": 60,
        "p_hPa": 934.917,
        "z_m": 228.5,
        "T_C": -0.44,
        "Td_C": -1.1,
        "wspd_kn": 16.7,
        "wdir_deg": 337.5
      },
      {
        "level_idx": 59,
        "p_hPa": 927.482,
        "z_m": 292.1,
        "T_C": -0.88,
        "Td_C": -1.36,
        "wspd_kn": 17.9,
        "wdir_deg": 343.1
      },
      {
        "level_idx": 58,
        "p_hPa": 919.502,
        "z_m": 360.9,
        "T_C": -1.29,
        "Td_C": -1.83,
        "wspd_kn": 18.4,
        "wdir_deg": 349.0
      },
      {
        "level_idx": 57,
        "p_hPa": 910.995,
        "z_m": 434.8,
        "T_C": -1.65,
        "Td_C": -2.67,
        "wspd_kn": 18.4,
        "wdir_deg": 354.8
      },
      {
        "level_idx": 56,
        "p_hPa": 901.998,
        "z_m": 513.6,
        "T_C": -2.02,
        "Td_C": -3.77,
        "wspd_kn": 17.7,
        "wdir_deg": 360.0
      },
      {
        "level_idx": 55,
        "p_hPa": 892.535,
        "z_m": 597.1,
        "T_C": -2.48,
        "Td_C": -4.8,
        "wspd_kn": 17.1,
        "wdir_deg": 3.9
      },
      {
        "level_idx": 54,
        "p_hPa": 882.639,
        "z_m": 685.3,
        "T_C": -2.91,
        "Td_C": -5.71,
        "wspd_kn": 16.9,
        "wdir_deg": 7.5
      },
      {
        "level_idx": 53,
        "p_hPa": 872.306,
        "z_m": 778.2,
        "T_C": -3.57,
        "Td_C": -6.21,
        "wspd_kn": 16.4,
        "wdir_deg": 9.0
      },
      {
        "level_idx": 52,
        "p_hPa": 861.561,
        "z_m": 875.8,
        "T_C": -4.34,
        "Td_C": -6.7,
        "wspd_kn": 15.8,
        "wdir_deg": 9.4
      },
      {
        "level_idx": 51,
        "p_hPa": 850.414,
        "z_m": 978.0,
        "T_C": -5.06,
        "Td_C": -7.18,
        "wspd_kn": 15.1,
        "wdir_deg": 9.6
      },
      {
        "level_idx": 50,
        "p_hPa": 838.864,
        "z_m": 1085.0,
        "T_C": -5.83,
        "Td_C": -7.41,
        "wspd_kn": 14.7,
        "wdir_deg": 8.6
      },
      {
        "level_idx": 49,
        "p_hPa": 826.931,
        "z_m": 1196.7,
        "T_C": -6.7,
        "Td_C": -7.76,
        "wspd_kn": 14.6,
        "wdir_deg": 6.6
      },
      {
        "level_idx": 48,
        "p_hPa": 814.618,
        "z_m": 1313.2,
        "T_C": -7.83,
        "Td_C": -8.17,
        "wspd_kn": 14.6,
        "wdir_deg": 6.7
      },
      {
        "level_idx": 47,
        "p_hPa": 801.928,
        "z_m": 1434.7,
        "T_C": -8.77,
        "Td_C": -9.26,
        "wspd_kn": 14.5,
        "wdir_deg": 5.1
      },
      {
        "level_idx": 46,
        "p_hPa": 788.877,
        "z_m": 1561.2,
        "T_C": -9.86,
        "Td_C": -9.88,
        "wspd_kn": 14.3,
        "wdir_deg": 4.0
      },
      {
        "level_idx": 45,
        "p_hPa": 775.477,
        "z_m": 1693.0,
        "T_C": -10.37,
        "Td_C": -11.25,
        "wspd_kn": 13.8,
        "wdir_deg": 357.4
      },
      {
        "level_idx": 44,
        "p_hPa": 761.752,
        "z_m": 1829.8,
        "T_C": -11.26,
        "Td_C": -12.52,
        "wspd_kn": 13.5,
        "wdir_deg": 351.9
      },
      {
        "level_idx": 43,
        "p_hPa": 747.703,
        "z_m": 1972.2,
        "T_C": -11.83,
        "Td_C": -13.76,
        "wspd_kn": 12.6,
        "wdir_deg": 347.1
      },
      {
        "level_idx": 42,
        "p_hPa": 733.343,
        "z_m": 2120.1,
        "T_C": -12.63,
        "Td_C": -15.4,
        "wspd_kn": 12.3,
        "wdir_deg": 340.0
      },
      {
        "level_idx": 41,
        "p_hPa": 718.673,
        "z_m": 2273.6,
        "T_C": -13.76,
        "Td_C": -18.36,
        "wspd_kn": 12.2,
        "wdir_deg": 336.8
      },
      {
        "level_idx": 40,
        "p_hPa": 703.682,
        "z_m": 2432.9,
        "T_C": -14.95,
        "Td_C": -20.73,
        "wspd_kn": 12.3,
        "wdir_deg": 329.6
      },
      {
        "level_idx": 39,
        "p_hPa": 688.388,
        "z_m": 2598.2,
        "T_C": -16.2,
        "Td_C": -21.99,
        "wspd_kn": 13.6,
        "wdir_deg": 334.2
      },
      {
        "level_idx": 38,
        "p_hPa": 672.796,
        "z_m": 2769.7,
        "T_C": -17.33,
        "Td_C": -24.7,
        "wspd_kn": 13.7,
        "wdir_deg": 337.7
      },
      {
        "level_idx": 37,
        "p_hPa": 656.936,
        "z_m": 2947.8,
        "T_C": -18.16,
        "Td_C": -30.42,
        "wspd_kn": 12.3,
        "wdir_deg": 337.9
      },
      {
        "level_idx": 36,
        "p_hPa": 640.834,
        "z_m": 3132.6,
        "T_C": -18.69,
        "Td_C": -37.44,
        "wspd_kn": 9.5,
        "wdir_deg": 335.3
      },
      {
        "level_idx": 35,
        "p_hPa": 624.512,
        "z_m": 3324.2,
        "T_C": -19.4,
        "Td_C": -41.3,
        "wspd_kn": 7.2,
        "wdir_deg": 320.7
      },
      {
        "level_idx": 34,
        "p_hPa": 607.991,
        "z_m": 3523.1,
        "T_C": -19.74,
        "Td_C": -40.84,
        "wspd_kn": 4.5,
        "wdir_deg": 299.7
      },
      {
        "level_idx": 33,
        "p_hPa": 591.286,
        "z_m": 3729.2,
        "T_C": -20.42,
        "Td_C": -38.87,
        "wspd_kn": 4.6,
        "wdir_deg": 251.5
      },
      {
        "level_idx": 32,
        "p_hPa": 574.385,
        "z_m": 3942.7,
        "T_C": -21.68,
        "Td_C": -37.99,
        "wspd_kn": 6.4,
        "wdir_deg": 256.2
      },
      {
        "level_idx": 31,
        "p_hPa": 557.277,
        "z_m": 4164.0,
        "T_C": -23.07,
        "Td_C": -39.56,
        "wspd_kn": 6.7,
        "wdir_deg": 236.4
      },
      {
        "level_idx": 30,
        "p_hPa": 539.969,
        "z_m": 4393.6,
        "T_C": -24.58,
        "Td_C": -41.2,
        "wspd_kn": 7.4,
        "wdir_deg": 228.4
      },
      {
        "level_idx": 29,
        "p_hPa": 522.479,
        "z_m": 4631.7,
        "T_C": -26.17,
        "Td_C": -40.79,
        "wspd_kn": 8.6,
        "wdir_deg": 225.7
      },
      {
        "level_idx": 28,
        "p_hPa": 504.815,
        "z_m": 4878.7,
        "T_C": -27.8,
        "Td_C": -38.99,
        "wspd_kn": 11.4,
        "wdir_deg": 215.7
      },
      {
        "level_idx": 27,
        "p_hPa": 486.998,
        "z_m": 5134.9,
        "T_C": -29.49,
        "Td_C": -40.04,
        "wspd_kn": 14.7,
        "wdir_deg": 211.7
      },
      {
        "level_idx": 26,
        "p_hPa": 469.055,
        "z_m": 5401.2,
        "T_C": -30.87,
        "Td_C": -46.21,
        "wspd_kn": 20.6,
        "wdir_deg": 206.5
      },
      {
        "level_idx": 25,
        "p_hPa": 451.007,
        "z_m": 5677.4,
        "T_C": -32.62,
        "Td_C": -50.88,
        "wspd_kn": 24.8,
        "wdir_deg": 199.2
      },
      {
        "level_idx": 24,
        "p_hPa": 432.867,
        "z_m": 5964.5,
        "T_C": -34.27,
        "Td_C": -46.36,
        "wspd_kn": 31.8,
        "wdir_deg": 207.5
      },
      {
        "level_idx": 23,
        "p_hPa": 414.635,
        "z_m": 6262.3,
        "T_C": -36.7,
        "Td_C": -42.2,
        "wspd_kn": 33.9,
        "wdir_deg": 204.2
      },
      {
        "level_idx": 22,
        "p_hPa": 396.3,
        "z_m": 6572.0,
        "T_C": -39.24,
        "Td_C": -52.54,
        "wspd_kn": 32.9,
        "wdir_deg": 205.6
      },
      {
        "level_idx": 21,
        "p_hPa": 377.873,
        "z_m": 6894.0,
        "T_C": -42.13,
        "Td_C": -51.05,
        "wspd_kn": 34.4,
        "wdir_deg": 199.7
      },
      {
        "level_idx": 20,
        "p_hPa": 359.376,
        "z_m": 7229.3,
        "T_C": -44.88,
        "Td_C": -49.42,
        "wspd_kn": 37.8,
        "wdir_deg": 213.0
      },
      {
        "level_idx": 19,
        "p_hPa": 340.864,
        "z_m": 7579.1,
        "T_C": -47.18,
        "Td_C": -51.12,
        "wspd_kn": 45.1,
        "wdir_deg": 218.0
      },
      {
        "level_idx": 18,
        "p_hPa": 322.385,
        "z_m": 7944.0,
        "T_C": -49.5,
        "Td_C": -53.95,
        "wspd_kn": 48.9,
        "wdir_deg": 218.9
      },
      {
        "level_idx": 17,
        "p_hPa": 304.012,
        "z_m": 8325.9,
        "T_C": -50.81,
        "Td_C": -65.52,
        "wspd_kn": 39.1,
        "wdir_deg": 228.0
      },
      {
        "level_idx": 16,
        "p_hPa": 285.891,
        "z_m": 8726.9,
        "T_C": -50.24,
        "Td_C": -75.42,
        "wspd_kn": 26.0,
        "wdir_deg": 241.7
      },
      {
        "level_idx": 15,
        "p_hPa": 268.147,
        "z_m": 9147.5,
        "T_C": -48.9,
        "Td_C": -77.68,
        "wspd_kn": 17.6,
        "wdir_deg": 277.4
      },
      {
        "level_idx": 14,
        "p_hPa": 250.803,
        "z_m": 9588.4,
        "T_C": -47.92,
        "Td_C": -78.74,
        "wspd_kn": 11.5,
        "wdir_deg": 304.7
      },
      {
        "level_idx": 13,
        "p_hPa": 233.85,
        "z_m": 10051.7,
        "T_C": -46.99,
        "Td_C": -79.78,
        "wspd_kn": 11.4,
        "wdir_deg": 300.9
      },
      {
        "level_idx": 12,
        "p_hPa": 217.253,
        "z_m": 10538.7,
        "T_C": -47.16,
        "Td_C": -79.9,
        "wspd_kn": 13.2,
        "wdir_deg": 326.1
      },
      {
        "level_idx": 11,
        "p_hPa": 201.002,
        "z_m": 11053.8,
        "T_C": -46.83,
        "Td_C": -80.65,
        "wspd_kn": 9.1,
        "wdir_deg": 329.8
      },
      {
        "level_idx": 10,
        "p_hPa": 185.084,
        "z_m": 11598.5,
        "T_C": -47.61,
        "Td_C": -82.22,
        "wspd_kn": 7.2,
        "wdir_deg": 311.2
      },
      {
        "level_idx": 9,
        "p_hPa": 169.48,
        "z_m": 12178.6,
        "T_C": -48.12,
        "Td_C": -83.19,
        "wspd_kn": 14.4,
        "wdir_deg": 286.9
      },
      {
        "level_idx": 8,
        "p_hPa": 154.241,
        "z_m": 12800.8,
        "T_C": -47.56,
        "Td_C": -84.48,
        "wspd_kn": 16.7,
        "wdir_deg": 283.5
      },
      {
        "level_idx": 7,
        "p_hPa": 139.336,
        "z_m": 13468.2,
        "T_C": -48.8,
        "Td_C": -85.37,
        "wspd_kn": 16.9,
        "wdir_deg": 296.8
      },
      {
        "level_idx": 6,
        "p_hPa": 124.664,
        "z_m": 14191.6,
        "T_C": -51.03,
        "Td_C": -85.21,
        "wspd_kn": 11.9,
        "wdir_deg": 310.0
      },
      {
        "level_idx": 5,
        "p_hPa": 110.143,
        "z_m": 14984.9,
        "T_C": -54.31,
        "Td_C": -86.13,
        "wspd_kn": 11.2,
        "wdir_deg": 289.6
      },
      {
        "level_idx": 4,
        "p_hPa": 95.766,
        "z_m": 15873.9,
        "T_C": -56.01,
        "Td_C": -87.47,
        "wspd_kn": 14.7,
        "wdir_deg": 321.5
      },
      {
        "level_idx": 3,
        "p_hPa": 81.447,
        "z_m": 16897.6,
        "T_C": -57.21,
        "Td_C": -87.76,
        "wspd_kn": 12.9,
        "wdir_deg": 350.8
      },
      {
        "level_idx": 2,
        "p_hPa": 66.82,
        "z_m": 18142.9,
        "T_C": -58.25,
        "Td_C": -88.52,
        "wspd_kn": 8.1,
        "wdir_deg": 356.4
      },
      {
        "level_idx": 1,
        "p_hPa": 48.651,
        "z_m": 20134.8,
        "T_C": -58.71,
        "Td_C": -89.98,
        "wspd_kn": 5.7,
        "wdir_deg": 355.3
      }
    ]
  },
  {
    "model": "ICON-D2",
    "run_date": "20260328",
    "run_hour": "15",
    "step_h": 18,
    "valid_time": "2026-03-29T09:00Z",
    "target_lat": 48.71,
    "target_lon": 8.784,
    "grid_lat": 48.71,
    "grid_lon": 8.784,
    "surface_p_hPa": 965.34,
    "n_levels_loaded": 65,
    "levels": [
      {
        "level_idx": 65,
        "p_hPa": 964.144,
        "z_m": 9.9,
        "T_C": 1.55,
        "Td_C": -0.75,
        "wspd_kn": 5.9,
        "wdir_deg": 333.1
      },
      {
        "level_idx": 64,
        "p_hPa": 961.023,
        "z_m": 36.0,
        "T_C": 1.11,
        "Td_C": -1.11,
        "wspd_kn": 7.4,
        "wdir_deg": 334.4
      },
      {
        "level_idx": 63,
        "p_hPa": 956.597,
        "z_m": 73.0,
        "T_C": 0.7,
        "Td_C": -1.26,
        "wspd_kn": 7.9,
        "wdir_deg": 334.7
      },
      {
        "level_idx": 62,
        "p_hPa": 951.197,
        "z_m": 118.3,
        "T_C": 0.23,
        "Td_C": -1.38,
        "wspd_kn": 8.2,
        "wdir_deg": 334.9
      },
      {
        "level_idx": 61,
        "p_hPa": 945.006,
        "z_m": 170.4,
        "T_C": -0.3,
        "Td_C": -1.5,
        "wspd_kn": 8.3,
        "wdir_deg": 334.9
      },
      {
        "level_idx": 60,
        "p_hPa": 938.147,
        "z_m": 228.5,
        "T_C": -0.87,
        "Td_C": -1.61,
        "wspd_kn": 8.4,
        "wdir_deg": 334.9
      },
      {
        "level_idx": 59,
        "p_hPa": 930.683,
        "z_m": 292.0,
        "T_C": -1.32,
        "Td_C": -2.39,
        "wspd_kn": 8.3,
        "wdir_deg": 338.2
      },
      {
        "level_idx": 58,
        "p_hPa": 922.655,
        "z_m": 360.9,
        "T_C": -1.63,
        "Td_C": -2.65,
        "wspd_kn": 7.6,
        "wdir_deg": 341.8
      },
      {
        "level_idx": 57,
        "p_hPa": 914.101,
        "z_m": 434.8,
        "T_C": -2.17,
        "Td_C": -3.0,
        "wspd_kn": 7.3,
        "wdir_deg": 345.6
      },
      {
        "level_idx": 56,
        "p_hPa": 905.055,
        "z_m": 513.5,
        "T_C": -2.72,
        "Td_C": -3.49,
        "wspd_kn": 7.0,
        "wdir_deg": 351.0
      },
      {
        "level_idx": 55,
        "p_hPa": 895.544,
        "z_m": 596.9,
        "T_C": -3.33,
        "Td_C": -4.0,
        "wspd_kn": 6.8,
        "wdir_deg": 356.1
      },
      {
        "level_idx": 54,
        "p_hPa": 885.569,
        "z_m": 685.2,
        "T_C": -3.96,
        "Td_C": -4.57,
        "wspd_kn": 6.8,
        "wdir_deg": 1.5
      },
      {
        "level_idx": 53,
        "p_hPa": 875.166,
        "z_m": 778.1,
        "T_C": -4.71,
        "Td_C": -5.04,
        "wspd_kn": 6.7,
        "wdir_deg": 5.0
      },
      {
        "level_idx": 52,
        "p_hPa": 864.341,
        "z_m": 875.6,
        "T_C": -5.46,
        "Td_C": -5.48,
        "wspd_kn": 6.7,
        "wdir_deg": 6.2
      },
      {
        "level_idx": 51,
        "p_hPa": 853.105,
        "z_m": 977.9,
        "T_C": -6.11,
        "Td_C": -6.13,
        "wspd_kn": 6.7,
        "wdir_deg": 9.6
      },
      {
        "level_idx": 50,
        "p_hPa": 841.48,
        "z_m": 1084.8,
        "T_C": -6.89,
        "Td_C": -7.09,
        "wspd_kn": 7.1,
        "wdir_deg": 18.0
      },
      {
        "level_idx": 49,
        "p_hPa": 829.477,
        "z_m": 1196.6,
        "T_C": -7.18,
        "Td_C": -9.67,
        "wspd_kn": 7.8,
        "wdir_deg": 21.9
      },
      {
        "level_idx": 48,
        "p_hPa": 817.123,
        "z_m": 1313.4,
        "T_C": -7.42,
        "Td_C": -13.01,
        "wspd_kn": 8.2,
        "wdir_deg": 21.5
      },
      {
        "level_idx": 47,
        "p_hPa": 804.413,
        "z_m": 1435.0,
        "T_C": -8.14,
        "Td_C": -15.42,
        "wspd_kn": 8.9,
        "wdir_deg": 19.7
      },
      {
        "level_idx": 46,
        "p_hPa": 791.349,
        "z_m": 1561.6,
        "T_C": -8.9,
        "Td_C": -18.63,
        "wspd_kn": 9.9,
        "wdir_deg": 18.6
      },
      {
        "level_idx": 45,
        "p_hPa": 777.945,
        "z_m": 1693.4,
        "T_C": -9.56,
        "Td_C": -23.41,
        "wspd_kn": 11.0,
        "wdir_deg": 16.2
      },
      {
        "level_idx": 44,
        "p_hPa": 764.209,
        "z_m": 1830.5,
        "T_C": -10.22,
        "Td_C": -26.54,
        "wspd_kn": 12.4,
        "wdir_deg": 18.1
      },
      {
        "level_idx": 43,
        "p_hPa": 750.153,
        "z_m": 1973.0,
        "T_C": -11.07,
        "Td_C": -28.61,
        "wspd_kn": 13.5,
        "wdir_deg": 20.0
      },
      {
        "level_idx": 42,
        "p_hPa": 735.771,
        "z_m": 2120.9,
        "T_C": -12.09,
        "Td_C": -31.09,
        "wspd_kn": 13.8,
        "wdir_deg": 21.9
      },
      {
        "level_idx": 41,
        "p_hPa": 721.073,
        "z_m": 2274.5,
        "T_C": -13.12,
        "Td_C": -32.96,
        "wspd_kn": 13.6,
        "wdir_deg": 27.1
      },
      {
        "level_idx": 40,
        "p_hPa": 706.071,
        "z_m": 2433.9,
        "T_C": -14.15,
        "Td_C": -33.42,
        "wspd_kn": 13.5,
        "wdir_deg": 30.7
      },
      {
        "level_idx": 39,
        "p_hPa": 690.762,
        "z_m": 2599.3,
        "T_C": -15.31,
        "Td_C": -34.44,
        "wspd_kn": 12.9,
        "wdir_deg": 31.8
      },
      {
        "level_idx": 38,
        "p_hPa": 675.164,
        "z_m": 2770.9,
        "T_C": -16.47,
        "Td_C": -37.43,
        "wspd_kn": 11.7,
        "wdir_deg": 31.2
      },
      {
        "level_idx": 37,
        "p_hPa": 659.294,
        "z_m": 2949.0,
        "T_C": -17.45,
        "Td_C": -40.53,
        "wspd_kn": 9.1,
        "wdir_deg": 30.2
      },
      {
        "level_idx": 36,
        "p_hPa": 643.167,
        "z_m": 3133.7,
        "T_C": -18.25,
        "Td_C": -41.12,
        "wspd_kn": 6.5,
        "wdir_deg": 20.7
      },
      {
        "level_idx": 35,
        "p_hPa": 626.817,
        "z_m": 3325.4,
        "T_C": -18.9,
        "Td_C": -43.12,
        "wspd_kn": 5.1,
        "wdir_deg": 357.4
      },
      {
        "level_idx": 34,
        "p_hPa": 610.269,
        "z_m": 3524.3,
        "T_C": -19.15,
        "Td_C": -43.72,
        "wspd_kn": 5.8,
        "wdir_deg": 322.4
      },
      {
        "level_idx": 33,
        "p_hPa": 593.533,
        "z_m": 3730.3,
        "T_C": -20.05,
        "Td_C": -44.59,
        "wspd_kn": 4.3,
        "wdir_deg": 299.4
      },
      {
        "level_idx": 32,
        "p_hPa": 576.595,
        "z_m": 3943.8,
        "T_C": -21.21,
        "Td_C": -44.23,
        "wspd_kn": 3.8,
        "wdir_deg": 265.0
      },
      {
        "level_idx": 31,
        "p_hPa": 559.463,
        "z_m": 4165.4,
        "T_C": -22.2,
        "Td_C": -40.96,
        "wspd_kn": 5.0,
        "wdir_deg": 250.3
      },
      {
        "level_idx": 30,
        "p_hPa": 542.151,
        "z_m": 4395.0,
        "T_C": -23.65,
        "Td_C": -38.76,
        "wspd_kn": 6.1,
        "wdir_deg": 213.4
      },
      {
        "level_idx": 29,
        "p_hPa": 524.649,
        "z_m": 4633.0,
        "T_C": -25.38,
        "Td_C": -39.67,
        "wspd_kn": 6.9,
        "wdir_deg": 210.0
      },
      {
        "level_idx": 28,
        "p_hPa": 506.977,
        "z_m": 4880.0,
        "T_C": -26.79,
        "Td_C": -41.64,
        "wspd_kn": 10.7,
        "wdir_deg": 209.1
      },
      {
        "level_idx": 27,
        "p_hPa": 489.16,
        "z_m": 5136.4,
        "T_C": -28.32,
        "Td_C": -42.5,
        "wspd_kn": 14.9,
        "wdir_deg": 212.2
      },
      {
        "level_idx": 26,
        "p_hPa": 471.199,
        "z_m": 5402.3,
        "T_C": -30.35,
        "Td_C": -40.41,
        "wspd_kn": 17.5,
        "wdir_deg": 217.5
      },
      {
        "level_idx": 25,
        "p_hPa": 453.098,
        "z_m": 5678.4,
        "T_C": -32.36,
        "Td_C": -48.24,
        "wspd_kn": 17.3,
        "wdir_deg": 222.7
      },
      {
        "level_idx": 24,
        "p_hPa": 434.872,
        "z_m": 5965.2,
        "T_C": -34.56,
        "Td_C": -49.27,
        "wspd_kn": 19.6,
        "wdir_deg": 218.1
      },
      {
        "level_idx": 23,
        "p_hPa": 416.528,
        "z_m": 6262.9,
        "T_C": -37.11,
        "Td_C": -47.76,
        "wspd_kn": 20.1,
        "wdir_deg": 226.1
      },
      {
        "level_idx": 22,
        "p_hPa": 398.07,
        "z_m": 6572.5,
        "T_C": -39.84,
        "Td_C": -48.05,
        "wspd_kn": 19.0,
        "wdir_deg": 229.5
      },
      {
        "level_idx": 21,
        "p_hPa": 379.572,
        "z_m": 6895.4,
        "T_C": -41.27,
        "Td_C": -58.67,
        "wspd_kn": 14.9,
        "wdir_deg": 236.1
      },
      {
        "level_idx": 20,
        "p_hPa": 361.13,
        "z_m": 7232.1,
        "T_C": -42.25,
        "Td_C": -67.22,
        "wspd_kn": 8.5,
        "wdir_deg": 272.3
      },
      {
        "level_idx": 19,
        "p_hPa": 342.778,
        "z_m": 7582.8,
        "T_C": -43.43,
        "Td_C": -71.58,
        "wspd_kn": 12.8,
        "wdir_deg": 333.5
      },
      {
        "level_idx": 18,
        "p_hPa": 324.54,
        "z_m": 7948.7,
        "T_C": -44.51,
        "Td_C": -75.11,
        "wspd_kn": 25.1,
        "wdir_deg": 356.1
      },
      {
        "level_idx": 17,
        "p_hPa": 306.427,
        "z_m": 8330.4,
        "T_C": -46.1,
        "Td_C": -75.32,
        "wspd_kn": 33.9,
        "wdir_deg": 3.5
      },
      {
        "level_idx": 16,
        "p_hPa": 288.449,
        "z_m": 8729.6,
        "T_C": -47.59,
        "Td_C": -75.62,
        "wspd_kn": 34.5,
        "wdir_deg": 6.0
      },
      {
        "level_idx": 15,
        "p_hPa": 270.636,
        "z_m": 9147.6,
        "T_C": -49.12,
        "Td_C": -76.16,
        "wspd_kn": 38.5,
        "wdir_deg": 5.0
      },
      {
        "level_idx": 14,
        "p_hPa": 253.022,
        "z_m": 9586.2,
        "T_C": -50.51,
        "Td_C": -76.31,
        "wspd_kn": 35.8,
        "wdir_deg": 4.3
      },
      {
        "level_idx": 13,
        "p_hPa": 235.687,
        "z_m": 10048.4,
        "T_C": -50.65,
        "Td_C": -78.15,
        "wspd_kn": 33.0,
        "wdir_deg": 358.1
      },
      {
        "level_idx": 12,
        "p_hPa": 218.725,
        "z_m": 10536.3,
        "T_C": -50.01,
        "Td_C": -79.18,
        "wspd_kn": 28.2,
        "wdir_deg": 354.7
      },
      {
        "level_idx": 11,
        "p_hPa": 202.168,
        "z_m": 11051.5,
        "T_C": -49.56,
        "Td_C": -79.64,
        "wspd_kn": 20.4,
        "wdir_deg": 349.0
      },
      {
        "level_idx": 10,
        "p_hPa": 186.009,
        "z_m": 11597.5,
        "T_C": -49.24,
        "Td_C": -81.75,
        "wspd_kn": 17.0,
        "wdir_deg": 348.5
      },
      {
        "level_idx": 9,
        "p_hPa": 170.224,
        "z_m": 12177.8,
        "T_C": -49.57,
        "Td_C": -83.23,
        "wspd_kn": 11.8,
        "wdir_deg": 350.1
      },
      {
        "level_idx": 8,
        "p_hPa": 154.775,
        "z_m": 12798.1,
        "T_C": -50.43,
        "Td_C": -84.64,
        "wspd_kn": 6.8,
        "wdir_deg": 337.1
      },
      {
        "level_idx": 7,
        "p_hPa": 139.665,
        "z_m": 13466.8,
        "T_C": -50.77,
        "Td_C": -85.69,
        "wspd_kn": 8.0,
        "wdir_deg": 304.5
      },
      {
        "level_idx": 6,
        "p_hPa": 124.861,
        "z_m": 14191.4,
        "T_C": -52.21,
        "Td_C": -86.27,
        "wspd_kn": 7.5,
        "wdir_deg": 279.2
      },
      {
        "level_idx": 5,
        "p_hPa": 110.315,
        "z_m": 14988.4,
        "T_C": -53.32,
        "Td_C": -86.43,
        "wspd_kn": 9.2,
        "wdir_deg": 278.8
      },
      {
        "level_idx": 4,
        "p_hPa": 95.985,
        "z_m": 15877.9,
        "T_C": -54.77,
        "Td_C": -87.0,
        "wspd_kn": 8.1,
        "wdir_deg": 318.7
      },
      {
        "level_idx": 3,
        "p_hPa": 81.642,
        "z_m": 16897.3,
        "T_C": -57.98,
        "Td_C": -87.8,
        "wspd_kn": 5.6,
        "wdir_deg": 326.2
      },
      {
        "level_idx": 2,
        "p_hPa": 66.949,
        "z_m": 18143.7,
        "T_C": -58.54,
        "Td_C": -88.57,
        "wspd_kn": 8.9,
        "wdir_deg": 333.0
      },
      {
        "level_idx": 1,
        "p_hPa": 48.718,
        "z_m": 20135.3,
        "T_C": -59.12,
        "Td_C": -89.98,
        "wspd_kn": 7.0,
        "wdir_deg": 39.9
      }
    ]
  },
  {
    "model": "ICON-D2",
    "run_date": "20260328",
    "run_hour": "15",
    "step_h": 24,
    "valid_time": "2026-03-29T15:00Z",
    "target_lat": 48.71,
    "target_lon": 8.784,
    "grid_lat": 48.71,
    "grid_lon": 8.784,
    "surface_p_hPa": 964.15,
    "n_levels_loaded": 65,
    "levels": [
      {
        "level_idx": 65,
        "p_hPa": 962.975,
        "z_m": 10.0,
        "T_C": 5.78,
        "Td_C": -4.27,
        "wspd_kn": 6.0,
        "wdir_deg": 336.8
      },
      {
        "level_idx": 64,
        "p_hPa": 959.907,
        "z_m": 36.0,
        "T_C": 5.33,
        "Td_C": -4.7,
        "wspd_kn": 7.4,
        "wdir_deg": 337.6
      },
      {
        "level_idx": 63,
        "p_hPa": 955.552,
        "z_m": 73.0,
        "T_C": 4.9,
        "Td_C": -4.88,
        "wspd_kn": 7.7,
        "wdir_deg": 337.7
      },
      {
        "level_idx": 62,
        "p_hPa": 950.231,
        "z_m": 118.4,
        "T_C": 4.42,
        "Td_C": -5.03,
        "wspd_kn": 7.9,
        "wdir_deg": 337.6
      },
      {
        "level_idx": 61,
        "p_hPa": 944.143,
        "z_m": 170.5,
        "T_C": 3.89,
        "Td_C": -5.17,
        "wspd_kn": 7.9,
        "wdir_deg": 337.4
      },
      {
        "level_idx": 60,
        "p_hPa": 937.391,
        "z_m": 228.6,
        "T_C": 3.3,
        "Td_C": -5.31,
        "wspd_kn": 7.9,
        "wdir_deg": 337.2
      },
      {
        "level_idx": 59,
        "p_hPa": 930.035,
        "z_m": 292.2,
        "T_C": 2.66,
        "Td_C": -5.46,
        "wspd_kn": 7.8,
        "wdir_deg": 336.8
      },
      {
        "level_idx": 58,
        "p_hPa": 922.116,
        "z_m": 361.1,
        "T_C": 1.98,
        "Td_C": -5.62,
        "wspd_kn": 7.7,
        "wdir_deg": 336.4
      },
      {
        "level_idx": 57,
        "p_hPa": 913.671,
        "z_m": 435.0,
        "T_C": 1.25,
        "Td_C": -5.79,
        "wspd_kn": 7.6,
        "wdir_deg": 335.9
      },
      {
        "level_idx": 56,
        "p_hPa": 904.736,
        "z_m": 513.7,
        "T_C": 0.47,
        "Td_C": -5.97,
        "wspd_kn": 7.4,
        "wdir_deg": 335.2
      },
      {
        "level_idx": 55,
        "p_hPa": 895.326,
        "z_m": 597.2,
        "T_C": -0.36,
        "Td_C": -6.18,
        "wspd_kn": 7.2,
        "wdir_deg": 334.3
      },
      {
        "level_idx": 54,
        "p_hPa": 885.462,
        "z_m": 685.3,
        "T_C": -1.22,
        "Td_C": -6.41,
        "wspd_kn": 6.9,
        "wdir_deg": 333.1
      },
      {
        "level_idx": 53,
        "p_hPa": 875.16,
        "z_m": 778.2,
        "T_C": -2.12,
        "Td_C": -6.79,
        "wspd_kn": 6.5,
        "wdir_deg": 331.3
      },
      {
        "level_idx": 52,
        "p_hPa": 864.436,
        "z_m": 875.7,
        "T_C": -3.02,
        "Td_C": -7.33,
        "wspd_kn": 6.0,
        "wdir_deg": 328.5
      },
      {
        "level_idx": 51,
        "p_hPa": 853.295,
        "z_m": 977.9,
        "T_C": -3.96,
        "Td_C": -7.87,
        "wspd_kn": 5.5,
        "wdir_deg": 323.4
      },
      {
        "level_idx": 50,
        "p_hPa": 841.753,
        "z_m": 1084.8,
        "T_C": -4.94,
        "Td_C": -8.33,
        "wspd_kn": 5.1,
        "wdir_deg": 318.9
      },
      {
        "level_idx": 49,
        "p_hPa": 829.817,
        "z_m": 1196.6,
        "T_C": -5.76,
        "Td_C": -8.73,
        "wspd_kn": 5.4,
        "wdir_deg": 323.2
      },
      {
        "level_idx": 48,
        "p_hPa": 817.513,
        "z_m": 1313.2,
        "T_C": -6.48,
        "Td_C": -8.44,
        "wspd_kn": 5.9,
        "wdir_deg": 341.0
      },
      {
        "level_idx": 47,
        "p_hPa": 804.839,
        "z_m": 1434.7,
        "T_C": -7.62,
        "Td_C": -8.74,
        "wspd_kn": 5.9,
        "wdir_deg": 342.9
      },
      {
        "level_idx": 46,
        "p_hPa": 791.802,
        "z_m": 1561.2,
        "T_C": -8.43,
        "Td_C": -10.36,
        "wspd_kn": 5.5,
        "wdir_deg": 347.0
      },
      {
        "level_idx": 45,
        "p_hPa": 778.411,
        "z_m": 1692.8,
        "T_C": -9.56,
        "Td_C": -10.89,
        "wspd_kn": 5.2,
        "wdir_deg": 350.3
      },
      {
        "level_idx": 44,
        "p_hPa": 764.669,
        "z_m": 1829.6,
        "T_C": -10.68,
        "Td_C": -11.73,
        "wspd_kn": 4.8,
        "wdir_deg": 358.9
      },
      {
        "level_idx": 43,
        "p_hPa": 750.575,
        "z_m": 1971.8,
        "T_C": -12.03,
        "Td_C": -12.06,
        "wspd_kn": 4.8,
        "wdir_deg": 0.2
      },
      {
        "level_idx": 42,
        "p_hPa": 736.145,
        "z_m": 2119.6,
        "T_C": -13.15,
        "Td_C": -13.18,
        "wspd_kn": 4.8,
        "wdir_deg": 0.4
      },
      {
        "level_idx": 41,
        "p_hPa": 721.442,
        "z_m": 2273.6,
        "T_C": -12.3,
        "Td_C": -23.68,
        "wspd_kn": 8.0,
        "wdir_deg": 359.7
      },
      {
        "level_idx": 40,
        "p_hPa": 706.518,
        "z_m": 2433.5,
        "T_C": -11.89,
        "Td_C": -30.77,
        "wspd_kn": 10.5,
        "wdir_deg": 359.3
      },
      {
        "level_idx": 39,
        "p_hPa": 691.321,
        "z_m": 2598.7,
        "T_C": -13.52,
        "Td_C": -31.08,
        "wspd_kn": 10.3,
        "wdir_deg": 359.5
      },
      {
        "level_idx": 38,
        "p_hPa": 675.813,
        "z_m": 2770.3,
        "T_C": -14.86,
        "Td_C": -38.89,
        "wspd_kn": 7.2,
        "wdir_deg": 357.5
      },
      {
        "level_idx": 37,
        "p_hPa": 660.025,
        "z_m": 2948.4,
        "T_C": -15.69,
        "Td_C": -41.46,
        "wspd_kn": 6.9,
        "wdir_deg": 338.3
      },
      {
        "level_idx": 36,
        "p_hPa": 644.012,
        "z_m": 3133.4,
        "T_C": -15.92,
        "Td_C": -42.9,
        "wspd_kn": 7.4,
        "wdir_deg": 320.3
      },
      {
        "level_idx": 35,
        "p_hPa": 627.803,
        "z_m": 3325.2,
        "T_C": -15.99,
        "Td_C": -43.21,
        "wspd_kn": 6.7,
        "wdir_deg": 281.1
      },
      {
        "level_idx": 34,
        "p_hPa": 611.42,
        "z_m": 3524.2,
        "T_C": -16.09,
        "Td_C": -40.46,
        "wspd_kn": 7.4,
        "wdir_deg": 235.6
      },
      {
        "level_idx": 33,
        "p_hPa": 594.823,
        "z_m": 3729.9,
        "T_C": -17.82,
        "Td_C": -38.26,
        "wspd_kn": 8.8,
        "wdir_deg": 226.3
      },
      {
        "level_idx": 32,
        "p_hPa": 577.965,
        "z_m": 3943.1,
        "T_C": -19.79,
        "Td_C": -37.73,
        "wspd_kn": 9.2,
        "wdir_deg": 231.8
      },
      {
        "level_idx": 31,
        "p_hPa": 560.874,
        "z_m": 4164.4,
        "T_C": -21.35,
        "Td_C": -37.61,
        "wspd_kn": 9.9,
        "wdir_deg": 249.2
      },
      {
        "level_idx": 30,
        "p_hPa": 543.581,
        "z_m": 4394.0,
        "T_C": -22.65,
        "Td_C": -37.4,
        "wspd_kn": 12.4,
        "wdir_deg": 265.4
      },
      {
        "level_idx": 29,
        "p_hPa": 526.144,
        "z_m": 4632.6,
        "T_C": -23.16,
        "Td_C": -42.31,
        "wspd_kn": 11.0,
        "wdir_deg": 286.0
      },
      {
        "level_idx": 28,
        "p_hPa": 508.624,
        "z_m": 4880.3,
        "T_C": -23.21,
        "Td_C": -54.83,
        "wspd_kn": 12.5,
        "wdir_deg": 342.7
      },
      {
        "level_idx": 27,
        "p_hPa": 491.049,
        "z_m": 5137.5,
        "T_C": -23.37,
        "Td_C": -60.07,
        "wspd_kn": 25.5,
        "wdir_deg": 12.9
      },
      {
        "level_idx": 26,
        "p_hPa": 473.424,
        "z_m": 5404.2,
        "T_C": -23.85,
        "Td_C": -58.51,
        "wspd_kn": 45.6,
        "wdir_deg": 23.8
      },
      {
        "level_idx": 25,
        "p_hPa": 455.71,
        "z_m": 5680.5,
        "T_C": -25.66,
        "Td_C": -53.92,
        "wspd_kn": 52.1,
        "wdir_deg": 23.6
      },
      {
        "level_idx": 24,
        "p_hPa": 437.887,
        "z_m": 5967.5,
        "T_C": -27.33,
        "Td_C": -46.86,
        "wspd_kn": 62.0,
        "wdir_deg": 20.1
      },
      {
        "level_idx": 23,
        "p_hPa": 419.971,
        "z_m": 6265.7,
        "T_C": -29.33,
        "Td_C": -46.43,
        "wspd_kn": 68.3,
        "wdir_deg": 19.2
      },
      {
        "level_idx": 22,
        "p_hPa": 401.972,
        "z_m": 6575.7,
        "T_C": -31.34,
        "Td_C": -52.12,
        "wspd_kn": 74.6,
        "wdir_deg": 16.5
      },
      {
        "level_idx": 21,
        "p_hPa": 383.902,
        "z_m": 6898.2,
        "T_C": -33.67,
        "Td_C": -53.27,
        "wspd_kn": 81.8,
        "wdir_deg": 15.7
      },
      {
        "level_idx": 20,
        "p_hPa": 365.756,
        "z_m": 7233.5,
        "T_C": -36.58,
        "Td_C": -51.0,
        "wspd_kn": 91.3,
        "wdir_deg": 15.9
      },
      {
        "level_idx": 19,
        "p_hPa": 347.53,
        "z_m": 7582.7,
        "T_C": -39.72,
        "Td_C": -51.51,
        "wspd_kn": 97.0,
        "wdir_deg": 11.1
      },
      {
        "level_idx": 18,
        "p_hPa": 329.276,
        "z_m": 7947.7,
        "T_C": -42.07,
        "Td_C": -54.65,
        "wspd_kn": 100.8,
        "wdir_deg": 8.1
      },
      {
        "level_idx": 17,
        "p_hPa": 311.019,
        "z_m": 8328.0,
        "T_C": -45.39,
        "Td_C": -55.92,
        "wspd_kn": 103.0,
        "wdir_deg": 6.3
      },
      {
        "level_idx": 16,
        "p_hPa": 292.767,
        "z_m": 8725.9,
        "T_C": -48.38,
        "Td_C": -57.62,
        "wspd_kn": 106.5,
        "wdir_deg": 4.9
      },
      {
        "level_idx": 15,
        "p_hPa": 274.562,
        "z_m": 9142.4,
        "T_C": -51.52,
        "Td_C": -61.59,
        "wspd_kn": 99.9,
        "wdir_deg": 5.4
      },
      {
        "level_idx": 14,
        "p_hPa": 256.401,
        "z_m": 9578.5,
        "T_C": -55.43,
        "Td_C": -64.88,
        "wspd_kn": 81.4,
        "wdir_deg": 8.5
      },
      {
        "level_idx": 13,
        "p_hPa": 238.429,
        "z_m": 10040.2,
        "T_C": -56.12,
        "Td_C": -71.28,
        "wspd_kn": 66.4,
        "wdir_deg": 359.4
      },
      {
        "level_idx": 12,
        "p_hPa": 220.863,
        "z_m": 10528.3,
        "T_C": -55.26,
        "Td_C": -75.68,
        "wspd_kn": 62.5,
        "wdir_deg": 358.0
      },
      {
        "level_idx": 11,
        "p_hPa": 203.727,
        "z_m": 11042.6,
        "T_C": -55.59,
        "Td_C": -80.21,
        "wspd_kn": 38.1,
        "wdir_deg": 7.5
      },
      {
        "level_idx": 10,
        "p_hPa": 187.086,
        "z_m": 11591.0,
        "T_C": -53.29,
        "Td_C": -82.18,
        "wspd_kn": 32.8,
        "wdir_deg": 357.0
      },
      {
        "level_idx": 9,
        "p_hPa": 170.962,
        "z_m": 12172.5,
        "T_C": -52.73,
        "Td_C": -82.67,
        "wspd_kn": 16.9,
        "wdir_deg": 359.1
      },
      {
        "level_idx": 8,
        "p_hPa": 155.289,
        "z_m": 12794.9,
        "T_C": -52.03,
        "Td_C": -83.83,
        "wspd_kn": 14.9,
        "wdir_deg": 319.7
      },
      {
        "level_idx": 7,
        "p_hPa": 140.057,
        "z_m": 13465.0,
        "T_C": -51.42,
        "Td_C": -85.0,
        "wspd_kn": 11.2,
        "wdir_deg": 299.9
      },
      {
        "level_idx": 6,
        "p_hPa": 125.177,
        "z_m": 14189.9,
        "T_C": -52.67,
        "Td_C": -85.97,
        "wspd_kn": 14.3,
        "wdir_deg": 283.0
      },
      {
        "level_idx": 5,
        "p_hPa": 110.545,
        "z_m": 14985.8,
        "T_C": -54.41,
        "Td_C": -86.58,
        "wspd_kn": 14.9,
        "wdir_deg": 299.6
      },
      {
        "level_idx": 4,
        "p_hPa": 96.139,
        "z_m": 15876.5,
        "T_C": -55.2,
        "Td_C": -87.03,
        "wspd_kn": 7.3,
        "wdir_deg": 304.6
      },
      {
        "level_idx": 3,
        "p_hPa": 81.761,
        "z_m": 16896.8,
        "T_C": -57.98,
        "Td_C": -87.69,
        "wspd_kn": 8.1,
        "wdir_deg": 300.1
      },
      {
        "level_idx": 2,
        "p_hPa": 67.059,
        "z_m": 18144.2,
        "T_C": -58.19,
        "Td_C": -88.5,
        "wspd_kn": 8.2,
        "wdir_deg": 346.0
      },
      {
        "level_idx": 1,
        "p_hPa": 48.821,
        "z_m": 20135.6,
        "T_C": -58.81,
        "Td_C": -89.97,
        "wspd_kn": 2.8,
        "wdir_deg": 6.7
      }
    ]
  }
]